{
 "name": "Game of Thrones", "size": 50000,
 "children": [
  {
   "name": "House and Character Details", "size": 10000,
   "children": [
    {
    },
   
    {
     "name": "Arryn", "size": 10000,
     "children": [
            {"name": "Albar Royce", "size": 7074},
			{"name": "Andar Royce", "size": 7074},
			{"name": "Anya Waynwood", "size": 7074},
			{"name": "Benedar Belmore", "size": 7074},
			{"name": "Byron", "size": 7074},
			{"name": "Eon Hunter", "size": 7074},
			{"name": "Gilwood Hunter", "size": 7074},
			{"name": "Gyles Grafton", "size": 7074},
			{"name": "Horton Redfort", "size": 7074},
			{"name": "Lyn Corbray", "size": 7074},
			{"name": "Marillion", "size": 7074},
			{"name": "Marwyn Belmore", "size": 7074},
			{"name": "Morton Waynwood", "size": 7074},
			{"name": "Mya Stone", "size": 7074},
			{"name": "Myranda Royce", "size": 7074},
			{"name": "Nestor Royce", "size": 7074},
			{"name": "Ossy", "size": 7074},
			{"name": "Raymar Royce", "size": 7074},
			{"name": "Symond Templeton", "size": 7074},
			{"name": "Terrance Lynderly", "size": 7074},
			{"name": "Vardis Egen", "size": 7074},
			{"name": "Willis Wode", "size": 7074},
			{"name": "Yohn Royce", "size": 7074}
     ]
    },
	
	
	{
     "name": "Baratheon", "size": 10000,
     "children": [
          {"name": "Aemon Estermont", "size": 7074},
		{"name": "Alesander Staedmon", "size": 7074},
		{"name": "Alester Florent", "size": 7074},
		{"name": "Allard Seaworth", "size": 7074},
		{"name": "Alyn Estermont", "size": 7074},
		{"name": "Andrew Estermont", "size": 7074},
		{"name": "Ardrian Celtigar", "size": 7074},
		{"name": "Axell Florent", "size": 7074},
		{"name": "Boros Blount", "size": 7074},
		{"name": "Bryan Fossoway", "size": 7074},
		{"name": "Bryce Caron", "size": 7074},
		{"name": "Bryen Farring", "size": 7074},
		{"name": "Clayton Suggs", "size": 7074},
		{"name": "Corliss Penny", "size": 7074},
		{"name": "Cortnay Penrose", "size": 7074},
		{"name": "Cressen", "size": 7074},
		{"name": "Dale Seaworth", "size": 7074},
		{"name": "Dalla (Dragonstone)", "size": 7074},
		{"name": "Davos Seaworth", "size": 7074},
		{"name": "Dermot", "size": 7074},
		{"name": "Devan Seaworth", "size": 7074},
		{"name": "Duram Bar Emmon", "size": 7074},
		{"name": "Elyas Willum", "size": 7074},
		{"name": "Emmon Cuy", "size": 7074},
		{"name": "Gerald Gower", "size": 7074},
		{"name": "Godry Farring", "size": 7074},
		{"name": "Guncer Sunglass", "size": 7074},
		{"name": "Guyard Morrigen", "size": 7074},
		{"name": "Hubard Rambton", "size": 7074},
		{"name": "Imry Florent", "size": 7074},
		{"name": "Jon Fossoway", "size": 7074},
		{"name": "Josua Willum", "size": 7074},
		{"name": "Justin Massey", "size": 7074},
		{"name": "Lamprey", "size": 7074},
		{"name": "Lorent Caswell", "size": 7074},
		{"name": "Mandon Moore", "size": 7074},
		{"name": "Matrice", "size": 7074},
		{"name": "Matthos Seaworth", "size": 7074},
		{"name": "Melisandre", "size": 7074},
		{"name": "Monford Velaryon", "size": 7074},
		{"name": "Moon Boy", "size": 7074},
		{"name": "Parmen Crane", "size": 7074},
		{"name": "Patchface", "size": 7074},
		{"name": "Patrek of King's Mountain", "size": 7074},
		{"name": "Porridge", "size": 7074},
		{"name": "Preston Greenfield", "size": 7074},
		{"name": "Pylos", "size": 7074},
		{"name": "Richard Horpe", "size": 7074},
		{"name": "Robar Royce", "size": 7074},
		{"name": "Ronnet Connington", "size": 7074},
		{"name": "Salladhor Saan", "size": 7074},
		{"name": "Selyse Florent", "size": 7074},
		{"name": "Shireen Baratheon", "size": 7074},
		{"name": "Shyra Errol", "size": 7074},
		{"name": "Tanton Fossoway", "size": 7074},
		{"name": "Timon", "size": 7074}
     ]
    },
   
    {
     "name": "Greyjoy", "size": 10000,
     "children": [
            {"name": "Ambrode", "size": 7074},
			{"name": "Andrik", "size": 7074},
			{"name": "Boremund Harlaw", "size": 7074},
			{"name": "Dagon Codd", "size": 7074},
			{"name": "Denys Drumm", "size": 7074},
			{"name": "Donnel Drumm", "size": 7074},
			{"name": "Dunstan Drumm", "size": 7074},
			{"name": "Dykk Harlaw", "size": 7074},
			{"name": "Eldred Codd", "size": 7074},
			{"name": "Emmond", "size": 7074},
			{"name": "Endehar", "size": 7074},
			{"name": "Erik Ironmaker", "size": 7074},
			{"name": "Esgred", "size": 7074},
			{"name": "Falia Flowers", "size": 7074},
			{"name": "Gevin Harlaw", "size": 7074},
			{"name": "Gormond Goodbrother", "size": 7074},
			{"name": "Gorold Goodbrother", "size": 7074},
			{"name": "Gran Goodbrother", "size": 7074},
			{"name": "Greydon Goodbrother", "size": 7074},
			{"name": "Gwin Goodbrother", "size": 7074},
			{"name": "Gylbert Farwynd", "size": 7074},
			{"name": "Gyles Farwynd", "size": 7074},
			{"name": "Gysella Goodbrother", "size": 7074},
			{"name": "Harmund Sharp", "size": 7074},
			{"name": "Harrag Sharp", "size": 7074},
			{"name": "Harras Harlaw", "size": 7074},
			{"name": "Joseran", "size": 7074},
			{"name": "Lenwood Tawney", "size": 7074},
			{"name": "Lorren", "size": 7074},
			{"name": "Lucas Codd", "size": 7074},
			{"name": "Maron Volmark", "size": 7074},
			{"name": "Meldred Merlyn", "size": 7074},
			{"name": "Moqorro", "size": 7074},
			{"name": "Murenmure", "size": 7074},
			{"name": "Norjen", "size": 7074},
			{"name": "Qarl Shepherd", "size": 7074},
			{"name": "Qarl the Maid", "size": 7074},
			{"name": "Quellon Humble", "size": 7074},
			{"name": "Ralf Kenning", "size": 7074},
			{"name": "Ralf Stonehouse", "size": 7074},
			{"name": "Ralf the Limper", "size": 7074},
			{"name": "Rodrik Harlaw", "size": 7074},
			{"name": "Rolfe", "size": 7074},
			{"name": "Romny Weaver", "size": 7074},
			{"name": "Sawane Botley", "size": 7074},
			{"name": "Sigfry Stonetree", "size": 7074},
			{"name": "Three-Tooth", "size": 7074},
			{"name": "Todric", "size": 7074},
			{"name": "Tristifer Botley", "size": 7074},
			{"name": "Ygon Farwynd", "size": 7074},
			{"name": "Yohn Farwynd", "size": 7074}
     ]
    },
	
	{
     "name": "House Arryn", "size": 10000,
     "children": [
           {"name": "Becca", "size": 7074},
			{"name": "Colemon", "size": 7074},
			{"name": "Hugh", "size": 7074},
			{"name": "Lysa Tully", "size": 7074},
			{"name": "Mela", "size": 7074},
			{"name": "Mord", "size": 7074},
			{"name": "Robert Arryn", "size": 7074}
     ]
    },
	
	    {
     "name": "House Baratheon", "size": 10000,
     "children": [
           {"name": "Colen of Greenpools", "size": 7074},
			{"name": "Edric Storm", "size": 7074},
			{"name": "Harwood Fell", "size": 7074},
			{"name": "Jate Blackberry", "size": 7074},
			{"name": "Jommy", "size": 7074},
			{"name": "Maric Seaworth", "size": 7074},
			{"name": "Renly Baratheon", "size": 7074},
			{"name": "Robert Baratheon", "size": 7074}
     ]
    },
	
	    {
     "name": "House Greyjoy", "size": 10000,
     "children": [
            {"name": "Adrack Humble", "size": 7074},
			{"name": "Aeron Greyjoy", "size": 7074},
			{"name": "Aggar", "size": 7074},
			{"name": "Asha Greyjoy", "size": 7074},
			{"name": "Cragorn", "size": 7074},
			{"name": "Dagmer", "size": 7074},
			{"name": "Drennan", "size": 7074},
			{"name": "Gelmarr", "size": 7074},
			{"name": "Gynir", "size": 7074},
			{"name": "Kenned", "size": 7074},
			{"name": "Kromm", "size": 7074},
			{"name": "Nute", "size": 7074},
			{"name": "Ragnor Pyke", "size": 7074},
			{"name": "Red Rolfe", "size": 7074},
			{"name": "Rolfe the Dwarf", "size": 7074},
			{"name": "Rymolf Stormdrunk", "size": 7074},
			{"name": "Squint", "size": 7074},
			{"name": "Stygg", "size": 7074},
			{"name": "Theon Greyjoy", "size": 7074},
			{"name": "Tymor", "size": 7074},
			{"name": "Ulf the Ill", "size": 7074},
			{"name": "Victarion Greyjoy", "size": 7074},
			{"name": "Werlag", "size": 7074},
			{"name": "Wulfe", "size": 7074}
     ]
    },
	
	    {
     "name": "House Lannister", "size": 10000,
     "children": [
            {"name": "Amory Lorch", "size": 7074},
			{"name": "Cadwyn", "size": 7074},
			{"name": "Cersei Lannister", "size": 7074},
			{"name": "Daven Lannister", "size": 7074},
			{"name": "Godwyn", "size": 7074},
			{"name": "Jate", "size": 7074},
			{"name": "Jodge", "size": 7074},
			{"name": "Joffrey Baratheon", "size": 7074},
			{"name": "Jyck", "size": 7074},
			{"name": "Kevan Lannister", "size": 7074},
			{"name": "Mallor", "size": 7074},
			{"name": "Morrec", "size": 7074},
			{"name": "Pycelle", "size": 7074},
			{"name": "Rolder", "size": 7074},
			{"name": "Rupert Brax", "size": 7074},
			{"name": "Senelle", "size": 7074},
			{"name": "Tregar", "size": 7074},
			{"name": "Tyrek Lannister", "size": 7074},
			{"name": "Tywin Lannister", "size": 7074},
			{"name": "Vylarr", "size": 7074},
			{"name": "Willem Lannister", "size": 7074}

     ]
    },
	
	    {
     "name": "House Martell", "size": 10000,
     "children": [
            {"name": "Areo Hotah", "size": 7074},
			{"name": "Arianne Martell", "size": 7074},
			{"name": "Caleotte", "size": 7074},
			{"name": "Mellei", "size": 7074},
			{"name": "Morra", "size": 7074},
			{"name": "Myles", "size": 7074},
			{"name": "Nymeria Sand", "size": 7074},
			{"name": "Obara Sand", "size": 7074},
			{"name": "Oberyn Martell", "size": 7074},
			{"name": "Ricasso", "size": 7074},
			{"name": "Sarella Sand", "size": 7074},
			{"name": "Tyene Sand", "size": 7074}
     ]
    },
	
	    {
     "name": "House Stark", "size": 10000,
     "children": [
    {"name": "Alebelly", "size": 7074},
{"name": "Alyn", "size": 7074},
{"name": "Barth (brewer)", "size": 7074},
{"name": "Bran Stark", "size": 7074},
{"name": "Catelyn Tully", "size": 7074},
{"name": "Cayn", "size": 7074},
{"name": "Desmond", "size": 7074},
{"name": "Donnis", "size": 7074},
{"name": "Eddard Stark", "size": 7074},
{"name": "Farlen", "size": 7074},
{"name": "Gage", "size": 7074},
{"name": "Gariss", "size": 7074},
{"name": "Heward", "size": 7074},
{"name": "Hodor", "size": 7074},
{"name": "Hullen", "size": 7074},
{"name": "Jacks", "size": 7074},
{"name": "Joseth", "size": 7074},
{"name": "Kyra", "size": 7074},
{"name": "Lew", "size": 7074},
{"name": "Luwin", "size": 7074},
{"name": "Mikken", "size": 7074},
{"name": "Mordane", "size": 7074},
{"name": "Murch (Winterfell)", "size": 7074},
{"name": "Nan", "size": 7074},
{"name": "Osha", "size": 7074},
{"name": "Palla", "size": 7074},
{"name": "Porther", "size": 7074},
{"name": "Poxy Tym", "size": 7074},
{"name": "Quent", "size": 7074},
{"name": "Rickon Stark", "size": 7074},
{"name": "Robb Stark", "size": 7074},
{"name": "Syrio Forel", "size": 7074},
{"name": "Tomard", "size": 7074},
{"name": "Wayn (guard)", "size": 7074},
{"name": "Wyl (guard)", "size": 7074}

     ]
    },
	
	    {
     "name": "House Targaryen", "size": 10000,
     "children": [
   {"name": "Aegon Targaryen", "size": 7074},
{"name": "Aggo", "size": 7074},
{"name": "Belwas", "size": 7074},
{"name": "Brynden Rivers", "size": 7074},
{"name": "Daenerys Targaryen", "size": 7074},
{"name": "Doreah", "size": 7074},
{"name": "Groleo", "size": 7074},
{"name": "Haldon", "size": 7074},
{"name": "Illyrio Mopatis", "size": 7074},
{"name": "Irri", "size": 7074},
{"name": "Jhiqui", "size": 7074},
{"name": "Jhogo", "size": 7074},
{"name": "Missandei", "size": 7074},
{"name": "Mossador", "size": 7074},
{"name": "Rakharo", "size": 7074},
{"name": "The Red Lamb", "size": 7074},
{"name": "Viserys Targaryen", "size": 7074},
{"name": "Yandry", "size": 7074},
{"name": "Ysilla", "size": 7074}

     ]
    },
	
	    {
     "name": "House Tully", "size": 10000,
     "children": [
   {"name": "Brynden Tully", "size": 7074},
{"name": "Delp", "size": 7074},
{"name": "Edmure Tully", "size": 7074},
{"name": "Elwood", "size": 7074},
{"name": "Enger", "size": 7074},
{"name": "Hoster Tully", "size": 7074},
{"name": "Myles", "size": 7074},
{"name": "Poul Pemford", "size": 7074}

     ]
    },
	
	    {
     "name": "House Tyrell", "size": 10000,
     "children": [
   {"name": "Alerie Hightower", "size": 7074},
{"name": "Alla Tyrell", "size": 7074},
{"name": "Arryk (Guard)", "size": 7074},
{"name": "Blue Bard", "size": 7074},
{"name": "Butterbumps", "size": 7074},
{"name": "Erryk (Guard)", "size": 7074},
{"name": "Garlan Tyrell", "size": 7074},
{"name": "Kerwin", "size": 7074},
{"name": "Mace Tyrell", "size": 7074},
{"name": "Margaery Tyrell", "size": 7074},
{"name": "Megga Tyrell", "size": 7074}

     ]
    },
	
	    {
     "name": "Lannister", "size": 10000,
     "children": [
   {"name": "Addam Marbrand", "size": 7074},
{"name": "Aemon Costayne", "size": 7074},
{"name": "Alyn Stackspear", "size": 7074},
{"name": "Antario Jast", "size": 7074},
{"name": "Arneld", "size": 7074},
{"name": "Aron Santagar", "size": 7074},
{"name": "Arys Oakheart", "size": 7074},
{"name": "Aurane Waters", "size": 7074},
{"name": "Ballabar", "size": 7074},
{"name": "Balon Swann", "size": 7074},
{"name": "Bonifer Hasty", "size": 7074},
{"name": "Bronn", "size": 7074},
{"name": "Burton Crakehall", "size": 7074},
{"name": "Chella", "size": 7074},
{"name": "Chiggen", "size": 7074},
{"name": "Conn", "size": 7074},
{"name": "Emmon Frey", "size": 7074},
{"name": "Falyse Stokeworth", "size": 7074},
{"name": "Flement Brax", "size": 7074},
{"name": "Forley Prester", "size": 7074},
{"name": "Frenken", "size": 7074},
{"name": "Garrett Paege", "size": 7074},
{"name": "Genna Lannister", "size": 7074},
{"name": "Gregor Clegane", "size": 7074},
{"name": "Gyles Rosby", "size": 7074},
{"name": "Hallyne", "size": 7074},
{"name": "Harys Swyft", "size": 7074},
{"name": "Humfrey Swyft", "size": 7074},
{"name": "Ilyn Payne", "size": 7074},
{"name": "Jacelyn Bywater", "size": 7074},
{"name": "Jaime Lannister", "size": 7074},
{"name": "Jocelyn Swyft", "size": 7074},
{"name": "Jon Bettley", "size": 7074},
{"name": "Josmyn Peckledon", "size": 7074},
{"name": "Joss Stilwood", "size": 7074},
{"name": "Jothos Slynt", "size": 7074},
{"name": "Kennos of Kayce", "size": 7074},
{"name": "Lambert Turnberry", "size": 7074},
{"name": "Lancel Lannister", "size": 7074},
{"name": "Leo Lefford", "size": 7074},
{"name": "Lewys Lydden", "size": 7074},
{"name": "Lewys Piper", "size": 7074},
{"name": "Lollys Stokeworth", "size": 7074},
{"name": "Lyle Crakehall", "size": 7074},
{"name": "Malliard", "size": 7074},
{"name": "Mathis Rowan", "size": 7074},
{"name": "Merlon Crakehall", "size": 7074},
{"name": "Meryn Trant", "size": 7074},
{"name": "Morros Slynt", "size": 7074},
{"name": "Munciter", "size": 7074},
{"name": "Myrcella Baratheon", "size": 7074},
{"name": "Orton Merryweather", "size": 7074},
{"name": "Osfryd Kettleblack", "size": 7074},
{"name": "Osmund Kettleblack", "size": 7074},
{"name": "Osney Kettleblack", "size": 7074},
{"name": "Philip Foote", "size": 7074},
{"name": "Podrick Payne", "size": 7074},
{"name": "Quenten Banefort", "size": 7074},
{"name": "Qyburn", "size": 7074},
{"name": "Robin Moreland", "size": 7074},
{"name": "Roger Hogg", "size": 7074},
{"name": "Roland Crakehall (Lord)", "size": 7074},
{"name": "Rolph Spicer", "size": 7074},
{"name": "Shae", "size": 7074},
{"name": "Shagga", "size": 7074},
{"name": "Steffon Swyft", "size": 7074},
{"name": "Sybell Spicer", "size": 7074},
{"name": "Symon Silver Tongue", "size": 7074},
{"name": "Taena of Myr", "size": 7074},
{"name": "Tallad", "size": 7074},
{"name": "Tanda Stokeworth", "size": 7074},
{"name": "Tickler", "size": 7074},
{"name": "Timett", "size": 7074},
{"name": "Tion Frey", "size": 7074},
{"name": "Tothmure", "size": 7074},
{"name": "Triston Sunderland", "size": 7074},
{"name": "Tyrion Lannister", "size": 7074},
{"name": "Tytos Brax", "size": 7074},
{"name": "Ulf son of Umar", "size": 7074},
{"name": "Weese", "size": 7074},
{"name": "Willit", "size": 7074}

     ]
    },
	
	    {
     "name": "Martell", "size": 10000,
     "children": [
 {"name": "Andrey Dalt", "size": 7074},
{"name": "Archibald Yronwood", "size": 7074},
{"name": "Arron Qorgyle", "size": 7074},
{"name": "Daemon Sand", "size": 7074},
{"name": "Deziel Dalt", "size": 7074},
{"name": "Dickon Manwoody", "size": 7074},
{"name": "Doran Martell", "size": 7074},
{"name": "Ellaria Sand", "size": 7074},
{"name": "Frynne", "size": 7074},
{"name": "Garin (Orphan)", "size": 7074},
{"name": "Gerold Dayne", "size": 7074},
{"name": "Gerris Drinkwater", "size": 7074},
{"name": "Jynessa Blackmont", "size": 7074},
{"name": "Larra Blackmont", "size": 7074},
{"name": "Mors Manwoody", "size": 7074},
{"name": "Myles Manwoody", "size": 7074},
{"name": "Myria Jordayne", "size": 7074},
{"name": "Nymella Toland", "size": 7074},
{"name": "Perros Blackmont", "size": 7074},
{"name": "Quentyn Martell", "size": 7074},
{"name": "Ryon Allyrion", "size": 7074},
{"name": "Sylva Santagar", "size": 7074},
{"name": "Tremond Gargalen", "size": 7074},
{"name": "Ulwyck Uller", "size": 7074},
{"name": "Willam Wells", "size": 7074}


     ]
    },
	
	    {
     "name": "Night's Watch", "size": 10000,
     "children": [
{"name": "Aemon Targaryen (son of Maekar I)", "size": 7074},
{"name": "Aethan", "size": 7074},
{"name": "Alan of Rosby", "size": 7074},
{"name": "Albett", "size": 7074},
{"name": "Alliser Thorne", "size": 7074},
{"name": "Arron", "size": 7074},
{"name": "Bannen", "size": 7074},
{"name": "Bass", "size": 7074},
{"name": "Bearded Ben", "size": 7074},
{"name": "Bedwyck", "size": 7074},
{"name": "Benjen Stark", "size": 7074},
{"name": "Black Bernarr", "size": 7074},
{"name": "Blane", "size": 7074},
{"name": "Borcas", "size": 7074},
{"name": "Bowen Marsh", "size": 7074},
{"name": "Brown Bernarr", "size": 7074},
{"name": "Byam Flint", "size": 7074},
{"name": "Cellador", "size": 7074},
{"name": "Chett", "size": 7074},
{"name": "Clubfoot Karl", "size": 7074},
{"name": "Clydas", "size": 7074},
{"name": "Conwy", "size": 7074},
{"name": "Cotter Pyke", "size": 7074},
{"name": "Cuger", "size": 7074},
{"name": "Dalbridge", "size": 7074},
{"name": "Dareon", "size": 7074},
{"name": "Denys Mallister", "size": 7074},
{"name": "Dick Follard", "size": 7074},
{"name": "Dirk", "size": 7074},
{"name": "Donal Noye", "size": 7074},
{"name": "Donnel Hill", "size": 7074},
{"name": "Dornish Dilly", "size": 7074},
{"name": "Dywen", "size": 7074},
{"name": "Easy", "size": 7074},
{"name": "Ebben", "size": 7074},
{"name": "Eddison Tollett", "size": 7074},
{"name": "Emrick", "size": 7074},
{"name": "Endrew Tarth", "size": 7074},
{"name": "Fornio", "size": 7074},
{"name": "Gared", "size": 7074},
{"name": "Garth Greyfeather", "size": 7074},
{"name": "Garth of Greenaway", "size": 7074},
{"name": "Garth of Oldtown", "size": 7074},
{"name": "Glendon Hewett", "size": 7074},
{"name": "Goady", "size": 7074},
{"name": "Grenn", "size": 7074},
{"name": "Grubbs", "size": 7074},
{"name": "Gueren", "size": 7074},
{"name": "Hairy Hal", "size": 7074},
{"name": "Hake", "size": 7074},
{"name": "Halder", "size": 7074},
{"name": "Hareth (Mole's Town)", "size": 7074},
{"name": "Harmune", "size": 7074},
{"name": "Hobb", "size": 7074},
{"name": "Hop-Robin", "size": 7074},
{"name": "Iron Emmett", "size": 7074},
{"name": "Jack Bulwer", "size": 7074},
{"name": "Jaremy Rykker", "size": 7074},
{"name": "Jarman Buckwell", "size": 7074},
{"name": "Jeor Mormont", "size": 7074},
{"name": "Jeren", "size": 7074},
{"name": "Jon Snow", "size": 7074},
{"name": "Kedge Whiteye", "size": 7074},
{"name": "Ketter", "size": 7074},
{"name": "Koss", "size": 7074},
{"name": "Kurz", "size": 7074},
{"name": "Lark", "size": 7074},
{"name": "Leathers", "size": 7074},
{"name": "Left Hand Lew", "size": 7074},
{"name": "Lommy", "size": 7074},
{"name": "Luke of Longtown", "size": 7074},
{"name": "Mallador Locke", "size": 7074},
{"name": "Maslyn", "size": 7074},
{"name": "Matthar", "size": 7074},
{"name": "Mawney", "size": 7074},
{"name": "Mully", "size": 7074},
{"name": "Murch", "size": 7074},
{"name": "Muttering Bill", "size": 7074},
{"name": "Old Henly", "size": 7074},
{"name": "Ollo Lophand", "size": 7074},
{"name": "Orphan Oss", "size": 7074},
{"name": "Othell Yarwyck", "size": 7074},
{"name": "Ottyn Wythers", "size": 7074},
{"name": "Owen", "size": 7074},
{"name": "Pate (Night's Watch)", "size": 7074},
{"name": "Pypar", "size": 7074},
{"name": "Qhorin Halfhand", "size": 7074},
{"name": "Qyle", "size": 7074},
{"name": "Rast", "size": 7074},
{"name": "Red Alyn", "size": 7074},
{"name": "Reysen", "size": 7074},
{"name": "Rolley", "size": 7074},
{"name": "Ronnel Harclay", "size": 7074},
{"name": "Rudge", "size": 7074},
{"name": "Rusty Flowers", "size": 7074},
{"name": "Samwell Tarly", "size": 7074},
{"name": "Satin", "size": 7074},
{"name": "Sawwood", "size": 7074},
{"name": "Small Paul", "size": 7074},
{"name": "Softfoot", "size": 7074},
{"name": "Spare Boot", "size": 7074},
{"name": "Spotted Pate of Maidenpool", "size": 7074},
{"name": "Stonesnake", "size": 7074},
{"name": "Thoren Smallwood", "size": 7074},
{"name": "Tim Tangletongue", "size": 7074},
{"name": "Todder", "size": 7074},
{"name": "Tumberjon", "size": 7074},
{"name": "Ulmer", "size": 7074},
{"name": "Urreg", "size": 7074},
{"name": "Watt", "size": 7074},
{"name": "Waymar Royce", "size": 7074},
{"name": "Will", "size": 7074},
{"name": "Woth", "size": 7074},
{"name": "Wynton Stout", "size": 7074},
{"name": "Yoren", "size": 7074},
{"name": "Young Henly", "size": 7074}

     ]
    },
	
	    {
     "name": "None", "size": 10000,
     "children": [
{"name": "Aegon Frey (Jinglebell)", "size": 7074},
{"name": "Aenys Frey", "size": 7074},
{"name": "Alayaya", "size": 7074},
{"name": "Alia of Braavos", "size": 7074},
{"name": "Alyx Frey", "size": 7074},
{"name": "Anguy", "size": 7074},
{"name": "Anvil Ryn", "size": 7074},
{"name": "Arwyn Frey", "size": 7074},
{"name": "Azzak", "size": 7074},
{"name": "Barra", "size": 7074},
{"name": "Barsena", "size": 7074},
{"name": "Becca the Baker", "size": 7074},
{"name": "Belaquo", "size": 7074},
{"name": "Bella", "size": 7074},
{"name": "Bellegere Otherys (courtesan)", "size": 7074},
{"name": "Bellonara Otherys", "size": 7074},
{"name": "Ben", "size": 7074},
{"name": "Ben Bones", "size": 7074},
{"name": "Ben Plumm", "size": 7074},
{"name": "Benfrey Frey", "size": 7074},
{"name": "Bennet", "size": 7074},
{"name": "Beric Dondarrion", "size": 7074},
{"name": "Bhakaz zo Loraq", "size": 7074},
{"name": "Big Walder Frey", "size": 7074},
{"name": "Biter", "size": 7074},
{"name": "Black Walder Frey", "size": 7074},
{"name": "Bloodbeard", "size": 7074},
{"name": "Brenett", "size": 7074},
{"name": "Brusco", "size": 7074},
{"name": "Bryen", "size": 7074},
{"name": "Byan Votyris", "size": 7074},
{"name": "Cersei Frey", "size": 7074},
{"name": "Chataya", "size": 7074},
{"name": "Chiswyck", "size": 7074},
{"name": "Cleos Frey", "size": 7074},
{"name": "Cohollo", "size": 7074},
{"name": "Coldhands", "size": 7074},
{"name": "Craster", "size": 7074},
{"name": "Creighton Longbough", "size": 7074},
{"name": "Cutjack", "size": 7074},
{"name": "Damon Dance-for-Me", "size": 7074},
{"name": "Damon Vypren", "size": 7074},
{"name": "Dancy", "size": 7074},
{"name": "Danwell Frey", "size": 7074},
{"name": "Dhazzar", "size": 7074},
{"name": "Dick Crabb", "size": 7074},
{"name": "Dobber", "size": 7074},
{"name": "Donnel Haigh", "size": 7074},
{"name": "Dontos Hollard", "size": 7074},
{"name": "Donyse", "size": 7074},
{"name": "Draqaz", "size": 7074},
{"name": "Dunsen", "size": 7074},
{"name": "Edric Dayne", "size": 7074},
{"name": "Edwyn Frey", "size": 7074},
{"name": "Eggon", "size": 7074},
{"name": "Elder Brother", "size": 7074},
{"name": "Elmar Frey", "size": 7074},
{"name": "Ermesande Hayford", "size": 7074},
{"name": "Erreck", "size": 7074},
{"name": "Fat Walda Frey", "size": 7074},
{"name": "Fletcher Will", "size": 7074},
{"name": "Fogo", "size": 7074},
{"name": "Galazza Galare", "size": 7074},
{"name": "Garse Goodbrook", "size": 7074},
{"name": "Gendry", "size": 7074},
{"name": "Gerren", "size": 7074},
{"name": "Ghael", "size": 7074},
{"name": "Ghost of High Heart", "size": 7074},
{"name": "Gillam", "size": 7074},
{"name": "Godric Borrell", "size": 7074},
{"name": "Goghor", "size": 7074},
{"name": "Grazdan", "size": 7074},
{"name": "Grazdan mo Eraz", "size": 7074},
{"name": "Grazdan mo Ullhor", "size": 7074},
{"name": "Grazdan zo Galare", "size": 7074},
{"name": "Grazdar zo Galare", "size": 7074},
{"name": "Grisel", "size": 7074},
{"name": "Grunt", "size": 7074},
{"name": "Haggo", "size": 7074},
{"name": "Hamish the Harper", "size": 7074},
{"name": "Harghaz", "size": 7074},
{"name": "Harra", "size": 7074},
{"name": "Hazzea", "size": 7074},
{"name": "Harry Strickland", "size": 7074},
{"name": "Harys Haigh", "size": 7074},
{"name": "Henly (Maester)", "size": 7074},
{"name": "High Sparrow", "size": 7074},
{"name": "Hod", "size": 7074},
{"name": "Holger", "size": 7074},
{"name": "Hosteen Frey", "size": 7074},
{"name": "Hot Pie", "size": 7074},
{"name": "Husband", "size": 7074},
{"name": "Hyle Hunt", "size": 7074},
{"name": "Iggo", "size": 7074},
{"name": "Ithoke", "size": 7074},
{"name": "Jack-Be-Lucky", "size": 7074},
{"name": "Jaggot", "size": 7074},
{"name": "Jalabhar Xho", "size": 7074},
{"name": "Janos Slynt", "size": 7074},
{"name": "Jaqen H'ghar", "size": 7074},
{"name": "Jared Frey", "size": 7074},
{"name": "Jhaqo", "size": 7074},
{"name": "Jhezane", "size": 7074},
{"name": "Joss", "size": 7074},
{"name": "Joyeuse Erenford", "size": 7074},
{"name": "Kella", "size": 7074},
{"name": "Kezmya", "size": 7074},
{"name": "Khorane Sathmantes", "size": 7074},
{"name": "Khrazz", "size": 7074},
{"name": "Kindly man", "size": 7074},
{"name": "Kojja Mo", "size": 7074},
{"name": "Kraznys mo Nakloz", "size": 7074},
{"name": "Kurleket", "size": 7074},
{"name": "Kyle (Banners)", "size": 7074},
{"name": "Lady of the Leaves", "size": 7074},
{"name": "Lanna (Happy Port)", "size": 7074},
{"name": "Lem", "size": 7074},
{"name": "Lennocks", "size": 7074},
{"name": "Lewis Lanster", "size": 7074},
{"name": "Little Walder Frey", "size": 7074},
{"name": "Lorcas", "size": 7074},
{"name": "Lothar Frey", "size": 7074},
{"name": "Lothor Brune", "size": 7074},
{"name": "Lucan", "size": 7074},
{"name": "Lucias Vypren", "size": 7074},
{"name": "Luco Prestayn", "size": 7074},
{"name": "Luton", "size": 7074},
{"name": "Lyonel", "size": 7074},
{"name": "Lysono Maar", "size": 7074},
{"name": "Mad Huntsman", "size": 7074},
{"name": "Maerie (Goodwife)", "size": 7074},
{"name": "Maerie (Whore)", "size": 7074},
{"name": "Mago", "size": 7074},
{"name": "Marei", "size": 7074},
{"name": "Marissa Frey", "size": 7074},
{"name": "Mariya Darry", "size": 7074},
{"name": "Martyn Rivers", "size": 7074},
{"name": "Marwyn", "size": 7074},
{"name": "Mathos Mallarawan", "size": 7074},
{"name": "Mebble", "size": 7074},
{"name": "Melly", "size": 7074},
{"name": "Meribald", "size": 7074},
{"name": "Mero", "size": 7074},
{"name": "Merrett Frey", "size": 7074},
{"name": "Mezzara", "size": 7074},
{"name": "Miklaz", "size": 7074},
{"name": "Mirri Maz Duur", "size": 7074},
{"name": "Mohor", "size": 7074},
{"name": "Mollander", "size": 7074},
{"name": "Moreo Tumitis", "size": 7074},
{"name": "Morgarth", "size": 7074},
{"name": "Moro", "size": 7074},
{"name": "Mudge (miller)", "size": 7074},
{"name": "Nage", "size": 7074},
{"name": "Narbert", "size": 7074},
{"name": "Nolla", "size": 7074},
{"name": "Nurse", "size": 7074},
{"name": "Notch", "size": 7074},
{"name": "Ogo", "size": 7074},
{"name": "Olyvar Frey", "size": 7074},
{"name": "Oppo", "size": 7074},
{"name": "Oswell Kettleblack", "size": 7074},
{"name": "Oznak zo Pahl", "size": 7074},
{"name": "Pate (novice)", "size": 7074},
{"name": "Pate (Lancewood)", "size": 7074},
{"name": "Pate (Old)", "size": 7074},
{"name": "Pello", "size": 7074},
{"name": "Penny", "size": 7074},
{"name": "Perwyn Frey", "size": 7074},
{"name": "Petyr Baelish", "size": 7074},
{"name": "Petyr Frey", "size": 7074},
{"name": "Pia", "size": 7074},
{"name": "Polliver", "size": 7074},
{"name": "Pono", "size": 7074},
{"name": "Praed", "size": 7074},
{"name": "Prendahl na Ghezn", "size": 7074},
{"name": "Pyat Pree", "size": 7074},
{"name": "Pyg", "size": 7074},
{"name": "Qezza", "size": 7074},
{"name": "Qotho", "size": 7074},
{"name": "Quaithe", "size": 7074},
{"name": "Quhuru Mo", "size": 7074},
{"name": "Rafford", "size": 7074},
{"name": "Ramsay Snow", "size": 7074},
{"name": "Randa", "size": 7074},
{"name": "Raymund Frey", "size": 7074},
{"name": "Reek", "size": 7074},
{"name": "Reznak mo Reznak", "size": 7074},
{"name": "Rhaegar Frey", "size": 7074},
{"name": "Rhogoro", "size": 7074},
{"name": "Rigney", "size": 7074},
{"name": "Rodrik Ryswell", "size": 7074},
{"name": "Ronald Storm", "size": 7074},
{"name": "Roose Ryswell", "size": 7074},
{"name": "Rorge", "size": 7074},
{"name": "Roslin Frey", "size": 7074},
{"name": "Ryger Rivers", "size": 7074},
{"name": "Ryman Frey", "size": 7074},
{"name": "Sallor", "size": 7074},
{"name": "Sandor Clegane", "size": 7074},
{"name": "Sarra Frey", "size": 7074},
{"name": "Sedgekins", "size": 7074},
{"name": "Serra Frey", "size": 7074},
{"name": "Shadrich", "size": 7074},
{"name": "Shagwell", "size": 7074},
{"name": "Sharna", "size": 7074},
{"name": "Shirei Frey", "size": 7074},
{"name": "Skahaz mo Kandaq", "size": 7074},
{"name": "Skinner", "size": 7074},
{"name": "Sour Alyn", "size": 7074},
{"name": "Spotted Cat", "size": 7074},
{"name": "Steelskin", "size": 7074},
{"name": "Sybassion", "size": 7074},
{"name": "Symond Frey", "size": 7074},
{"name": "Ternesio Terys", "size": 7074},
{"name": "Theo Frey", "size": 7074},
{"name": "Theomore Lannister", "size": 7074},
{"name": "Thoros", "size": 7074},
{"name": "Three Toes", "size": 7074},
{"name": "Timeon", "size": 7074},
{"name": "Tobho Mott", "size": 7074},
{"name": "Tom of Sevenstreams", "size": 7074},
{"name": "Torrek", "size": 7074},
{"name": "Tuffleberry", "size": 7074},
{"name": "Tybero Istarion", "size": 7074},
{"name": "Tycho Nestoris", "size": 7074},
{"name": "Tyta Frey", "size": 7074},
{"name": "Tytos Frey", "size": 7074},
{"name": "Umar", "size": 7074},
{"name": "Umfred", "size": 7074},
{"name": "Unella", "size": 7074},
{"name": "Urswyck", "size": 7074},
{"name": "Utt", "size": 7074},
{"name": "Vargo Hoat", "size": 7074},
{"name": "Waif", "size": 7074},
{"name": "Walda Rivers (daughter of Aemon)", "size": 7074},
{"name": "Walder Frey", "size": 7074},
{"name": "Walder Rivers", "size": 7074},
{"name": "Walton", "size": 7074},
{"name": "Wat (orphan)", "size": 7074},
{"name": "Wat (sailor)", "size": 7074},
{"name": "Watty", "size": 7074},
{"name": "Weasel", "size": 7074},
{"name": "Wendello Qar Deeth", "size": 7074},
{"name": "Whalen Frey", "size": 7074},
{"name": "Will (orphan)", "size": 7074},
{"name": "Wyl the Whittler", "size": 7074},
{"name": "Xaro Xhoan Daxos", "size": 7074},
{"name": "Xhondo", "size": 7074},
{"name": "Yellow Dick", "size": 7074},
{"name": "Zollo", "size": 7074},
{"name": "Yurkhaz zo Yunzak", "size": 7074},
{"name": "Yezzan Zo Qaggaz", "size": 7074}

     ]
    },
	
	    {
     "name": "Stark", "size": 10000,
     "children": [
{"name": "Alys Karstark", "size": 7074},
{"name": "Alysane Mormont", "size": 7074},
{"name": "Arnolf Karstark", "size": 7074},
{"name": "Arthor Karstark", "size": 7074},
{"name": "Arya Stark", "size": 7074},
{"name": "Barbrey Dustin", "size": 7074},
{"name": "Benfred Tallhart", "size": 7074},
{"name": "Bessa (Winterfell)", "size": 7074},
{"name": "Beth Cassel", "size": 7074},
{"name": "Brandon Norrey", "size": 7074},
{"name": "Brienne of Tarth", "size": 7074},
{"name": "Chayle", "size": 7074},
{"name": "Cley Cerwyn", "size": 7074},
{"name": "Cregan Karstark", "size": 7074},
{"name": "Dacey Mormont", "size": 7074},
{"name": "Daryn Hornwood", "size": 7074},
{"name": "Donella Hornwood", "size": 7074},
{"name": "Donnel Locke", "size": 7074},
{"name": "Dudley", "size": 7074},
{"name": "Eddard Karstark", "size": 7074},
{"name": "Eleyna Westerling", "size": 7074},
{"name": "Galbart Glover", "size": 7074},
{"name": "Gawen Westerling", "size": 7074},
{"name": "Gladden Wylde", "size": 7074},
{"name": "Hallis Mollen", "size": 7074},
{"name": "Halys Hornwood", "size": 7074},
{"name": "Harrion Karstark", "size": 7074},
{"name": "Harwin", "size": 7074},
{"name": "Harwood Stout", "size": 7074},
{"name": "Helman Tallhart", "size": 7074},
{"name": "Hother Umber", "size": 7074},
{"name": "Jason Mallister", "size": 7074},
{"name": "Jeyne Poole", "size": 7074},
{"name": "Jeyne Westerling", "size": 7074},
{"name": "Jojen Reed", "size": 7074},
{"name": "Jon Umber (Greatjon)", "size": 7074},
{"name": "Jon Umber (Smalljon)", "size": 7074},
{"name": "Jonelle Cerwyn", "size": 7074},
{"name": "Jory Cassel", "size": 7074},
{"name": "Leobald Tallhart", "size": 7074},
{"name": "Leona Woolfield", "size": 7074},
{"name": "Lharys", "size": 7074},
{"name": "Maege Mormont", "size": 7074},
{"name": "Marlon Manderly", "size": 7074},
{"name": "Medger Cerwyn", "size": 7074},
{"name": "Meera Reed", "size": 7074},
{"name": "Meliana", "size": 7074},
{"name": "Mors Umber", "size": 7074},
{"name": "Mycah", "size": 7074},
{"name": "Ondrew Locke", "size": 7074},
{"name": "Raynald Westerling", "size": 7074},
{"name": "Rickard Karstark", "size": 7074},
{"name": "Rickard Ryswell", "size": 7074},
{"name": "Robett Glover", "size": 7074},
{"name": "Robin Flint", "size": 7074},
{"name": "Rodrik Cassel", "size": 7074},
{"name": "Roger Ryswell", "size": 7074},
{"name": "Rollam Westerling", "size": 7074},
{"name": "Roose Bolton", "size": 7074},
{"name": "Sansa Stark", "size": 7074},
{"name": "Stevron Frey", "size": 7074},
{"name": "Sybelle Glover", "size": 7074},
{"name": "Theodan Wells", "size": 7074},
{"name": "Torrhen Karstark", "size": 7074},
{"name": "Vayon Poole", "size": 7074},
{"name": "Wendel Manderly", "size": 7074},
{"name": "Wex Pyke", "size": 7074},
{"name": "Wilbert", "size": 7074},
{"name": "Wylis Manderly", "size": 7074},
{"name": "Wylla Manderly", "size": 7074},
{"name": "Wyman Manderly", "size": 7074},
{"name": "Wynafryd Manderly", "size": 7074},
{"name": "Zei", "size": 7074}


     ]
    },
	
	    {
     "name": "Targaryen", "size": 10000,
     "children": [
{"name": "Barristan Selmy", "size": 7074},
{"name": "Daario Naharis", "size": 7074},
{"name": "Drogo", "size": 7074},
{"name": "Eroeh", "size": 7074},
{"name": "Ezzara", "size": 7074},
{"name": "Grey Worm", "size": 7074},
{"name": "Jon Connington", "size": 7074},
{"name": "Jorah Mormont", "size": 7074},
{"name": "Larraq", "size": 7074},
{"name": "Quaro", "size": 7074},
{"name": "Raymun Darry", "size": 7074},
{"name": "Rolly Duckfield", "size": 7074},
{"name": "Stalwart Shield", "size": 7074},
{"name": "Symon Stripeback", "size": 7074},
{"name": "Tal Toraq", "size": 7074},
{"name": "Tumco Lho", "size": 7074},
{"name": "Varys", "size": 7074}

     ]
    },
	
	
	    {
     "name": "Tully", "size": 10000,
     "children": [
{"name": "Clement Piper", "size": 7074},
{"name": "Desmond Grell", "size": 7074},
{"name": "Donnel Waynwood", "size": 7074},
{"name": "Hugo Vance", "size": 7074},
{"name": "Jonos Bracken", "size": 7074},
{"name": "Karyl Vance", "size": 7074},
{"name": "Lucas Blackwood", "size": 7074},
{"name": "Lyman Darry", "size": 7074},
{"name": "Lymond Goodbrook", "size": 7074},
{"name": "Lymond Lychester", "size": 7074},
{"name": "Mark Mullendore", "size": 7074},
{"name": "Marq Piper", "size": 7074},
{"name": "Masha Heddle", "size": 7074},
{"name": "Owen Norrey", "size": 7074},
{"name": "Patrek Mallister", "size": 7074},
{"name": "Ravella Swann", "size": 7074},
{"name": "Robin Ryger", "size": 7074},
{"name": "Tytos Blackwood", "size": 7074},
{"name": "Utherydes Wayn", "size": 7074},
{"name": "Vyman", "size": 7074},
{"name": "William Mooton", "size": 7074},
{"name": "Willum", "size": 7074}

     ]
    },
	
	    {
     "name": "Tyrell", "size": 10000,
     "children": [
{"name": "Alyn Ambrose", "size": 7074},
{"name": "Arwyn Oakheart", "size": 7074},
{"name": "Bayard Norcross", "size": 7074},
{"name": "Elinor Tyrell", "size": 7074},
{"name": "Hobber Redwyne", "size": 7074},
{"name": "Horas Redwyne", "size": 7074},
{"name": "Janna Tyrell", "size": 7074},
{"name": "Leo Tyrell", "size": 7074},
{"name": "Leonette Fossoway", "size": 7074},
{"name": "Loras Tyrell", "size": 7074},
{"name": "Meredyth Crane", "size": 7074},
{"name": "Olenna Redwyne", "size": 7074},
{"name": "Paxter Redwyne", "size": 7074},
{"name": "Randyll Tarly", "size": 7074},
{"name": "Talbert Serry", "size": 7074}
     ]
    },
	
	    {
     "name": "Wildling", "size": 10000,
     "children": [
{"name": "Arson", "size": 7074},
{"name": "Big Boil", "size": 7074},
{"name": "Borroq", "size": 7074},
{"name": "Dalla", "size": 7074},
{"name": "Del", "size": 7074},
{"name": "Frenya", "size": 7074},
{"name": "Gilly", "size": 7074},
{"name": "Grigg", "size": 7074},
{"name": "Hali", "size": 7074},
{"name": "Harma", "size": 7074},
{"name": "Holly", "size": 7074},
{"name": "Howd Wanderer", "size": 7074},
{"name": "Jarl", "size": 7074},
{"name": "Lord of Bones", "size": 7074},
{"name": "Mag Mar Tun Doh Weg", "size": 7074},
{"name": "Mance Rayder", "size": 7074},
{"name": "Maris", "size": 7074},
{"name": "Meha", "size": 7074},
{"name": "Monster", "size": 7074},
{"name": "Morna White Mask", "size": 7074},
{"name": "Myrtle", "size": 7074},
{"name": "Orell", "size": 7074},
{"name": "Quort", "size": 7074},
{"name": "Ragwyle", "size": 7074},
{"name": "Rowan", "size": 7074},
{"name": "Ryk", "size": 7074},
{"name": "Squirrel", "size": 7074},
{"name": "Stiv", "size": 7074},
{"name": "Stone Thumbs", "size": 7074},
{"name": "Styr", "size": 7074},
{"name": "Thistle", "size": 7074},
{"name": "Tormund", "size": 7074},
{"name": "Val", "size": 7074},
{"name": "Varamyr", "size": 7074},
{"name": "Wallen", "size": 7074},
{"name": "Weeper", "size": 7074},
{"name": "Willow Witch-eye", "size": 7074},
{"name": "Wun Weg Wun Dar Wun", "size": 7074},
{"name": "Ygritte", "size": 7074},
{"name": "Torwynd the Tame", "size": 7074}


     ]
    }
	
   ]
  }
 ]
}